{"Bond, Devante CHI LB": [], "Bonnafon, Reggie CAR RB": ["2 Receptions ", "3 Rushing Yards ", "39 Receiving Yards ", "2 Rushes ", "0 Fumbles Lost (to Opponent) "], "Booker, Devontae DEN RB": ["2 Receptions ", "17 Receiving Yards ", "0 Fumbles Lost (to Opponent) "], "Boone, Mike MIN RB": ["2 Receptions ", "148 Rushing Yards ", "12 Receiving Yards ", "1 Rushing TDs ", "17 Rushes ", "0 Fumbles Lost (to Opponent) ", "1 Tackles "], "Borders, Breon WAS CB": [], "Bortles, Blake LAR QB": [], "Bosa, Joey LAC DE": ["1 Tackles ", "2 Assists "], "Bosa, Nick SFO DE": ["5 Tackles ", "1 Assists "], "Bosher, Matt ATL PN": [], "Bostic, Jon WAS LB": ["2 Assists ", "4 Tackles "], "Boston, Tre CAR S": ["1 Assists ", "4 Tackles ", "3 Passes Defensed "], "Boswell, Chris PIT PK": [], "Bourne, Kendrick SFO WR": [], "Bouye, A.J. JAC CB": [], "Bower, Tashawn FA DE": ["Bye Week"], "Bowman, Navorro FA LB": ["Bye Week"], "Bowser, Tyus BAL LB": [], "Boyd, Kris MIN CB": ["2 Tackles for a Loss ", "8 Tackles ", "1 Passes Defensed "], "Boyd, Tyler CIN WR": ["5 Receptions ", "59 Receiving Yards ", "0 Fumbles Lost (to Opponent) ", "5 Receptions "], "Boykin, Miles BAL WR": [], "Boyle, Nick BAL TE": ["0 Fumbles Lost (to Opponent) ", "1 Tackles ", "6 Receiving Yards ", "1 Receptions "], "Boyle, Tim GBP QB": [], "Bradberry, James CAR CB": ["2 Passes Defensed "], "Bradford, Sam FA QB": ["Bye Week"], "Bradham, Nigel PHI LB": ["5 Assists ", "5 Tackles "], "Brady, Tom NEP QB": ["2 Passing TDs ", "1 Interceptions ", "221 Passing Yards ", "0 Fumbles Lost (to Opponent) "], "Brady, Tyre FA WR": ["Bye Week"], "Brailford, Jordan WAS LB": [], "Branch, Andre FA DE": ["Bye Week"], "Branch, Tyvon FA S": ["Bye Week"], "Brantley, Caleb WAS DE": [], "Brate, Cameron TBB TE": ["1 Receiving TDs ", "0 Fumbles Lost (to Opponent) ", "2 Receiving Yards ", "1 Receptions "], "Braunecker, Ben CHI TE": [], "Bray, Tyler FA QB": ["Bye Week"], "Breeland, Bashaud KCC CB": ["2 Tackles ", "1 Assists "], "Brees, Drew NOS QB": ["-1 Rushing Yards ", "3 Passing TDs ", "0 Interceptions ", "253 Passing Yards ", "1 Rushes ", "0 Fumbles Lost (to Opponent) "], "Breida, Matt SFO RB": ["16 Rushing Yards ", "4 Rushes ", "0 Fumbles Lost (to Opponent) "], "Brent, K.J. FA WR": ["Bye Week"], "Brewer, Aaron ARI LB": [], "Brice, Kentrell FA S": ["Bye Week"], "Bridgewater, Teddy NOS QB": ["-3 Rushing Yards ", "0 Interceptions ", "14 Passing Yards ", "3 Rushes ", "0 Fumbles Lost (to Opponent) "], "Brinkley, Beau TEN TE": [], "Brissett, Jacoby IND QB": ["17 Rushing Yards ", "0 Interceptions ", "162 Passing Yards ", "4 Rushes ", "2 Fumbles Lost (to Opponent) "], "Britt, Kenny FA WR": ["Bye Week"], "Brock, Tramaine TEN CB": ["5 Tackles ", "1 Assists "], "Brockers, Michael LAR DE": ["2 Assists "], "Bromley, Jay FA DT": ["Bye Week"], "Broncos, Denver DEN Def": ["0 Fumbles Lost on Defense ", "1 Fumble Recoveries on Defense ", "12 Opponent Fumble Recovery Yards ", "1 Forced Fumbles ", "2 Sacked a QB ", "477 Total Net Yards Allowed ", "15 Offensive Points Against ", "18 Opponent First Downs ", "5 Opponent Third Down Conversions ", "11 Opponent Third Downs Failed ", "2 Opponent Fourth Downs Failed ", "1 Opponent Fourth Down Conversions "], "Broncos, Denver DEN Off": ["9 Sack Yards Lost ", "3 Fumbles on Offense ", "1 yd Passing TD ", "168 Passing Yards ", "17 Completions ", "11 Incomplete Passes ", "0 Interceptions ", "70 Rushing Yards ", "1 Fumbles Lost on Offense ", "16 First Downs ", "3 Third Down Conversions ", "9 Third Downs Failed "], "Broncos, Denver DEN ST": ["1 Punts Inside 20 ", "1 Fumbles on Special Teams ", "1 Extra Points ", "43 yd Field Goal ", "49 yd Field Goal ", "51 yd Field Goal ", "57 yd Field Goal Miss ", "4 Punt Return Yards ", "28 Kickoff Return Yards ", "0 Fumbles Lost on Special Teams ", "61 Penalty Yards "], "Broncos, Denver DEN TM": [], "Broncos, Denver DEN TMDB": [], "Broncos, Denver DEN TMDL": [], "Broncos, Denver DEN TMLB": ["16 Assists ", "3 Tackles for a Loss ", "2 Passes Defensed ", "1.0 Sacked a QB ", "19 Tackles "], "Broncos, Denver DEN TMPK": [], "Broncos, Denver DEN TMPN": [], "Broncos, Denver DEN TMQB": ["29 Rushing Yards ", "1 Passing TDs ", "0 Interceptions ", "177 Passing Yards ", "6 Rushes ", "1 Fumbles Lost (to Opponent) "], "Broncos, Denver DEN TMRB": ["3 Receptions ", "49 Rushing Yards ", "25 Receiving Yards ", "20 Rushes ", "0 Fumbles Lost (to Opponent) "], "Broncos, Denver DEN TMTE": ["1 Receiving TDs ", "0 Fumbles Lost (to Opponent) ", "1 Tackles ", "21 Receiving Yards ", "4 Receptions "], "Broncos, Denver DEN TMWR": ["10 Receptions ", "-8 Rushing Yards ", "131 Receiving Yards ", "4 Punt Return Yards ", "28 Kickoff Return Yards ", "1 Rushes ", "0 Fumbles Lost (to Opponent) ", "1 Tackles ", "10 Receptions "], "Brooks, Nate MIA CB": ["3 Tackles ", "1 Passes Defensed "], "Brooks, Terrence NEP S": [], "Brooks-James, Tony FA RB": ["Bye Week"], "Brossette, Nick FA RB": ["Bye Week"], "Brothers, Kentrell MIN LB": ["3 Assists ", "6 Tackles "], "Broughton, Cortez LAC DE": [], "Brown, A.J. TEN WR": ["4 Receptions ", "1 Receiving TDs ", "124 Receiving Yards ", "0 Fumbles Lost (to Opponent) ", "4 Receptions "], "Brown, Alex KCC CB": [], "Brown, Andrew CIN DT": [], "Brown, Anthony DAL CB": [], "Brown, Antonio FA* WR": ["Bye Week"], "Brown, Billy IND TE": [], "Brown, Blair FA LB": ["Bye Week"], "Brown, Daniel NYJ TE": ["0 Fumbles Lost (to Opponent) ", "32 Receiving Yards ", "3 Receptions "], "Brown, Fadol FA DE": ["Bye Week"], "Brown, Fred DEN WR": ["1 Tackles "], "Brown, Jaron SEA WR": [], "Brown, Jatavis LAC LB": ["1 Tackles "], "Brown, Jayon TEN LB": ["1 Assists ", "2 Tackles "], "Brown, John BUF WR": [], "Brown, Jon FA PK": ["Bye Week"], "Brown, Jordan FA CB": ["Bye Week"], "Brown, Kyron NYJ CB": [], "Brown, Mack FA RB": ["Bye Week"], "Brown, Malcolm LAR RB": ["1 Receptions ", "26 Rushing Yards ", "6 Receiving Yards ", "1 Rushing TDs ", "9 Rushes ", "0 Fumbles Lost (to Opponent) "], "Brown, Malcom NOS DT": ["1 Tackles ", "1 Assists ", "1 Fumble Recoveries (from Opponent) "], "Brown, Marquise BAL WR": ["2 Receptions ", "15 Receiving Yards ", "0 Fumbles Lost (to Opponent) ", "2 Receptions "], "Brown, Miles ARI DT": ["1 Assists "], "Brown, Noah DAL WR": [], "Brown, Pharaoh CLE TE": [], "Brown, Preston JAC LB": [], "Brown, Tony FA CB": ["Bye Week"], "Brown, Zach FA LB": ["Bye Week"], "Browning, Jake FA QB": ["Bye Week"], "Browns, Cleveland CLE Def": ["1 Interceptions ", "0 Fumbles Lost on Defense ", "1 Sacked a QB ", "361 Total Net Yards Allowed ", "33 Offensive Points Against ", "22 Opponent First Downs ", "9 Opponent Third Down Conversions ", "5 Opponent Third Downs Failed ", " Opponent Fourth Downs Failed ", " Opponent Fourth Down Conversions "], "Browns, Cleveland CLE Off": ["40 Sack Yards Lost ", "1 Fumbles on Offense ", "20 yd Passing TD ", "46 yd Passing TD ", "56 yd Passing TD ", "239 Passing Yards ", "12 Completions ", "15 Incomplete Passes ", "3 Interceptions ", "74 Rushing Yards ", "0 Fumbles Lost on Offense ", "15 First Downs ", "4 Third Down Conversions ", "9 Third Downs Failed ", "1 Fourth Down Conversions "], "Browns, Cleveland CLE ST": ["2 Punts Inside 20 ", "1 Extra Points Missed ", "2 Extra Points ", "42 yd Field Goal ", "9 Punt Return Yards ", "95 Kickoff Return Yards ", "0 Fumbles Lost on Special Teams ", "33 Penalty Yards "], "Browns, Cleveland CLE TM": [], "Browns, Cleveland CLE TMDB": [], "Browns, Cleveland CLE TMDL": [], "Browns, Cleveland CLE TMLB": ["11 Assists ", "2 Tackles for a Loss ", "15 Tackles "], "Browns, Cleveland CLE TMPK": [], "Browns, Cleveland CLE TMPN": [], "Browns, Cleveland CLE TMQB": ["29 Rushing Yards ", "3 Passing TDs ", "3 Interceptions ", "279 Passing Yards ", "4 Rushes ", "0 Fumbles Lost (to Opponent) "], "Browns, Cleveland CLE TMRB": ["4 Receptions ", "45 Rushing Yards ", "33 Receiving Yards ", "9 Punt Return Yards ", "76 Kickoff Return Yards ", "1 Assists ", "16 Rushes ", "0 Fumbles Lost (to Opponent) ", "1 Tackles "], "Browns, Cleveland CLE TMTE": [], "Browns, Cleveland CLE TMWR": ["8 Receptions ", "3 Receiving TDs ", "246 Receiving Yards ", "0 Fumbles Lost (to Opponent) ", "1 Tackles ", "8 Receptions "], "Bryan, Taven JAC DT": ["3 Tackles ", "1 Assists ", "1 Tackles for a Loss ", "1 Forced Fumbles ", "1 Passes Defensed ", "1.0 Sacked a QB "], "Bryant, Austin DET DE": ["1 Tackles ", "3 Assists "], "Bryant, Brandin FA DT": ["Bye Week"], "Bryant, Dez FA WR": ["Bye Week"], "Bryant, Martavis FA WR": ["Bye Week"], "Bryant, Matt FA PK": ["Bye Week"], "Bryant, Ventell DAL WR": [], "Bucannon, Deone NYG LB": ["1 Tackles for a Loss ", "2 Tackles "], "Buccaneers, Tampa Bay TBB Def": ["0 Fumbles Lost on Defense ", "1 Fumble Recoveries on Defense ", "91 Opponent Fumble Recovery Yards ", "1 Forced Fumbles ", "6 Sacked a QB ", "373 Total Net Yards Allowed ", "91 yd Defensive TD ", "22 Offensive Points Against ", "28 Opponent First Downs ", "7 Opponent Third Down Conversions ", "11 Opponent Third Downs Failed ", "2 Opponent Fourth Downs Failed ", "1 Opponent Fourth Down Conversions "], "Buccaneers, Tampa Bay TBB Off": ["8 Sack Yards Lost ", "1 Rushing 2 Pointers ", "2 Fumbles on Offense ", "2 yd Passing TD ", "24 yd Passing TD ", "193 Passing Yards ", "13 Completions ", "11 Incomplete Passes ", "2 Interceptions ", "136 Rushing Yards ", "1 Fumbles Lost on Offense ", "14 First Downs ", "1 Third Down Conversions ", "7 Third Downs Failed ", "1 Fourth Down Conversions "], "Buccaneers, Tampa Bay TBB ST": ["1 Fumbles on Special Teams ", "2 Extra Points ", "49 yd Field Goal Miss ", "34 yd Field Goal Miss ", "44 yd Field Goal Miss ", "61 Kickoff Return Yards ", "0 Fumbles Lost on Special Teams ", "97 Penalty Yards "], "Buccaneers, Tampa Bay TBB TM": [], "Buccaneers, Tampa Bay TBB TMDB": [], "Buccaneers, Tampa Bay TBB TMDL": [], "Buccaneers, Tampa Bay TBB TMLB": ["4 Assists ", "3 Tackles for a Loss ", "1 Defensive Fumble Recovery TDs ", "1 Fumble Recoveries (from Opponent) ", "3.0 Sacked a QB ", "17 Tackles "], "Buccaneers, Tampa Bay TBB TMPK": [], "Buccaneers, Tampa Bay TBB TMPN": [], "Buccaneers, Tampa Bay TBB TMQB": ["5 Rushing Yards ", "1 Rushing 2 Pointers ", "2 Passing TDs ", "2 Interceptions ", "201 Passing Yards ", "2 Rushes ", "0 Fumbles Lost (to Opponent) "], "Buccaneers, Tampa Bay TBB TMRB": ["4 Receptions ", "120 Rushing Yards ", "35 Receiving Yards ", "61 Kickoff Return Yards ", "18 Rushes ", "1 Fumbles Lost (to Opponent) ", "1 Tackles "], "Buccaneers, Tampa Bay TBB TMTE": ["1 Receiving TDs ", "0 Fumbles Lost (to Opponent) ", "2 Receiving Yards ", "1 Receptions "], "Buccaneers, Tampa Bay TBB TMWR": ["8 Receptions ", "1 Receiving TDs ", "164 Receiving Yards ", "0 Fumbles Lost (to Opponent) ", "2 Tackles ", "8 Receptions "], "Buckner, DeForest SFO DT": ["2 Tackles ", "2 Assists ", "1 Tackles for a Loss ", "1.0 Sacked a QB "], "Buggs, Isaiah PIT DE": ["1 Tackles "], "Bullard, Jonathan ARI DE": [], "Bullock, Randy CIN PK": [], "Bullough, Riley FA LB": ["Bye Week"], "Burbridge, Aaron FA WR": ["Bye Week"], "Burfict, Vontaze OAK LB": [], "Burgess, James NYJ LB": ["2 Assists ", "1 Tackles for a Loss ", "1 Interceptions ", "1 Passes Defensed ", "7 Tackles "], "Burkhead, Rex NEP RB": ["1 Receptions ", "48 Rushing Yards ", "6 Receiving Yards ", "6 Rushes ", "0 Fumbles Lost (to Opponent) "], "Burks, Oren GBP LB": [], "Burnett, Deontay PHI WR": ["2 Receptions ", "48 Receiving Yards ", "0 Fumbles Lost (to Opponent) ", "2 Receptions "], "Burnett, Morgan CLE S": [], "Burns, Artie PIT CB": [], "Burns, Brian CAR DE": ["1 Tackles ", "1 Assists ", "1 Tackles for a Loss ", "1.0 Sacked a QB "], "Burr-Kirven, Ben SEA LB": [], "Burris, Juston CLE CB": ["1 Tackles ", "1 Assists ", "2 Passes Defensed "], "Burton, Michael WAS RB": ["1 Tackles "], "Burton, Trey CHI TE": [], "Bush, Deon CHI S": [], "Bush, Devin PIT LB": ["1 Assists ", "11 Tackles "], "Bush, Rafael FA S": ["Bye Week"], "Butker, Harrison KCC PK": [], "Butler, Adam NEP DT": ["1 Tackles ", "1 Tackles for a Loss "], "Butler, Brice FA WR": ["Bye Week"], "Butler, Emmanuel FA WR": ["Bye Week"], "Butler, Hakeem ARI WR": [], "Butler, Malcolm TEN CB": [], "Butler, Vernon CAR DT": ["1 Assists "], "Butt, Jake DEN TE": [], "Byard, Kevin TEN S": ["1 Interceptions ", "1 Assists ", "6 Tackles ", "1 Passes Defensed "], "Bynes, Josh BAL LB": ["2 Assists "], "Byrd, Damiere ARI WR": ["7 Receptions ", "1 Receiving TDs ", "74 Receiving Yards ", "1 Fumbles Lost (to Opponent) ", "7 Receptions "], "Cabinda, Jason DET LB": ["1 Tackles "], "Cadet, Travaris FA RB": ["Bye Week"], "Cain, Deon PIT WR": [], "Caldwell, Josh FA RB": ["Bye Week"], "Calhoun, Shilique NEP DE": [], "Calitro, Austin JAC LB": ["2 Assists ", "1 Tackles for a Loss ", "3 Tackles "], "Callahan, Bill WAS Coach": [], "Callahan, Bryce DEN CB": [], "Callahan, Joe FA QB": ["Bye Week"], "Callaway, Antonio FA WR": ["Bye Week"], "Campanaro, Michael FA WR": ["Bye Week"], "Campbell, Calais JAC DE": ["1 Tackles ", "1 Assists ", "1 Fumble Recoveries (from Opponent) ", "1 Defensive Fumble Recovery TDs "], "Campbell, De'Vondre ATL LB": ["1 Assists ", "1 Tackles for a Loss ", "2 Tackles "], "Campbell, Ibraheim GBP S": ["1 Tackles "], "Campbell, Parris IND WR": [], "Canady, Maurice NYJ CB": ["1 Tackles ", "1 Assists "], "Cannon, KD FA WR": ["Bye Week"], "Cannon, Trenton NYJ RB": [], "Cantrell, Dylan LAC WR": [], "Cardinals, Arizona ARI Def": ["0 Fumbles Lost on Defense ", "1 Sacked a QB ", "424 Total Net Yards Allowed ", "31 Offensive Points Against ", "25 Opponent First Downs ", "11 Opponent Third Down Conversions ", "7 Opponent Third Downs Failed ", "1 Opponent Fourth Downs Failed ", " Opponent Fourth Down Conversions "], "Cardinals, Arizona ARI Off": ["3 Sack Yards Lost ", "3 Fumbles on Offense ", "3 yd Passing TD ", "23 yd Passing TD ", "322 Passing Yards ", "27 Completions ", "16 Incomplete Passes ", "2 Interceptions ", "1 yd Rushing TD ", "71 Rushing Yards ", "3 Fumbles Lost on Offense ", "22 First Downs ", "5 Third Down Conversions ", "5 Third Downs Failed "], "Cardinals, Arizona ARI ST": ["2 Punts Inside 20 ", "3 Extra Points ", "31 yd Field Goal ", "68 Kickoff Return Yards ", "0 Fumbles Lost on Special Teams ", "63 Penalty Yards "], "Cardinals, Arizona ARI TM": [], "Cardinals, Arizona ARI TMDB": [], "Cardinals, Arizona ARI TMDL": [], "Cardinals, Arizona ARI TMLB": ["13 Assists ", "3 Tackles for a Loss ", "2 Passes Defensed ", "19 Tackles "], "Cardinals, Arizona ARI TMPK": [], "Cardinals, Arizona ARI TMPN": [], "Cardinals, Arizona ARI TMQB": ["6 Rushing Yards ", "2 Passing TDs ", "2 Interceptions ", "325 Passing Yards ", "3 Rushes ", "2 Fumbles Lost (to Opponent) "], "Cardinals, Arizona ARI TMRB": ["3 Receptions ", "59 Rushing Yards ", "23 Receiving Yards ", "1 Rushing TDs ", "13 Rushes ", "0 Fumbles Lost (to Opponent) ", "2 Tackles "], "Cardinals, Arizona ARI TMTE": ["1 Receiving TDs ", "0 Fumbles Lost (to Opponent) ", "99 Receiving Yards ", "5 Receptions "], "Cardinals, Arizona ARI TMWR": ["19 Receptions ", "6 Rushing Yards ", "1 Receiving TDs ", "203 Receiving Yards ", "68 Kickoff Return Yards ", "1 Rushes ", "1 Fumbles Lost (to Opponent) ", "1 Tackles ", "19 Receptions "], "Carlson, Daniel OAK PK": [], "Carlson, Stephen CLE TE": [], "Carr, Austin NOS WR": [], "Carr, Brandon BAL CB": ["2 Tackles for a Loss ", "1 Safeties ", "1.0 Sacked a QB ", "3 Tackles ", "1 Assists "], "Carr, Derek OAK QB": ["1 Passing TDs ", "0 Interceptions ", "391 Passing Yards ", "1 Rushes ", "0 Fumbles Lost (to Opponent) "], "Carradine, Cornellius FA DE": ["Bye Week"], "Carrie, Travis CLE CB": [], "Carrier, Derek OAK TE": ["0 Fumbles Lost (to Opponent) ", "4 Receiving Yards ", "1 Receptions "], "Carroll, Pete SEA Coach": [], "Carroo, Leonte FA WR": ["Bye Week"], "Carson, Chris SEA RB": [], "Carson, Tra FA RB": ["Bye Week"], "Carter, Bruce FA LB": ["Bye Week"], "Carter, Cethan CIN TE": ["1 Tackles "], "Carter, DeAndre HOU WR": ["6 Receptions ", "65 Receiving Yards ", "25 Punt Return Yards ", "0 Fumbles Lost (to Opponent) ", "6 Receptions "], "Carter, Jamal ATL S": ["1 Assists "], "Carter, Jermaine CAR LB": ["3 Assists ", "1 Tackles for a Loss ", "8 Tackles "], "Carter, Lorenzo NYG LB": ["1 Tackles for a Loss ", "2 Tackles "], "Carter, Martez FA RB": ["Bye Week"], "Casey, Jurrell TEN DE": ["2 Tackles ", "2 Assists ", "1 Tackles for a Loss ", "1.0 Sacked a QB "], "Cashman, Blake NYJ LB": [], "Cassel, Matt FA QB": ["Bye Week"], "Catanzaro, Chandler FA PK": ["Bye Week"], "Celek, Garrett SFO TE": [], "Chancellor, Kam FA S": ["Bye Week"], "Chandler, Sean NYG S": ["1 Tackles "], "Chargers, Los Angeles LAC Def": ["1 Interceptions ", "0 Fumbles Lost on Defense ", "15 Interception Return Yards ", "0 Sacked a QB ", "336 Total Net Yards Allowed ", "24 Offensive Points Against ", "16 Opponent First Downs ", "7 Opponent Third Down Conversions ", "3 Opponent Third Downs Failed ", " Opponent Fourth Downs Failed ", " Opponent Fourth Down Conversions "], "Chargers, Los Angeles LAC Off": ["23 Sack Yards Lost ", "2 Fourth Downs Failed ", "8 yd Passing TD ", "12 yd Passing TD ", "258 Passing Yards ", "31 Completions ", "15 Incomplete Passes ", "2 Interceptions ", "5 yd Rushing TD ", "108 Rushing Yards ", "0 Fumbles Lost on Offense ", "25 First Downs ", "8 Third Down Conversions ", "7 Third Downs Failed ", "2 Fourth Down Conversions "], "Chargers, Los Angeles LAC ST": ["2 Punts Inside 20 ", "3 Extra Points ", "99 Kickoff Return Yards ", "0 Fumbles Lost on Special Teams ", "40 Penalty Yards "], "Chargers, Los Angeles LAC TM": [], "Chargers, Los Angeles LAC TMDB": [], "Chargers, Los Angeles LAC TMDL": [], "Chargers, Los Angeles LAC TMLB": ["3 Assists ", "1 Passes Defensed ", "13 Tackles "], "Chargers, Los Angeles LAC TMPK": [], "Chargers, Los Angeles LAC TMPN": [], "Chargers, Los Angeles LAC TMQB": ["5 Rushing Yards ", "2 Passing TDs ", "2 Interceptions ", "281 Passing Yards ", "1 Rushes ", "0 Fumbles Lost (to Opponent) "], "Chargers, Los Angeles LAC TMRB": ["15 Receptions ", "103 Rushing Yards ", "119 Receiving Yards ", "1 Rushing TDs ", "86 Kickoff Return Yards ", "24 Rushes ", "0 Fumbles Lost (to Opponent) "], "Chargers, Los Angeles LAC TMTE": ["1 Receiving TDs ", "0 Fumbles Lost (to Opponent) ", "42 Receiving Yards ", "5 Receptions "], "Chargers, Los Angeles LAC TMWR": ["11 Receptions ", "1 Receiving TDs ", "120 Receiving Yards ", "0 Fumbles Lost (to Opponent) ", "2 Tackles ", "11 Receptions "], "Chark, D.J. JAC WR": ["4 Receptions ", "34 Receiving Yards ", "0 Fumbles Lost (to Opponent) ", "4 Receptions "], "Charles, Jamaal FA RB": ["Bye Week"], "Charles, Orson FA TE": ["Bye Week"], "Charlton, Taco MIA DE": [], "Chesson, Jehu FA WR": ["Bye Week"], "Chickillo, Anthony PIT LB": ["2 Tackles "], "Chiefs, Kansas City KCC Def": ["2 Interceptions ", "0 Fumbles Lost on Defense ", "6 Interception Return Yards ", "3 Sacked a QB ", "366 Total Net Yards Allowed ", "21 Offensive Points Against ", "25 Opponent First Downs ", "8 Opponent Third Down Conversions ", "7 Opponent Third Downs Failed ", "2 Opponent Fourth Downs Failed ", "2 Opponent Fourth Down Conversions "], "Chiefs, Kansas City KCC Off": ["0 Sack Yards Lost ", "24 yd Passing TD ", "174 Passing Yards ", "16 Completions ", "9 Incomplete Passes ", "1 Interceptions ", "7 yd Rushing TD ", "84 yd Rushing TD ", "162 Rushing Yards ", "0 Fumbles Lost on Offense ", "16 First Downs ", "7 Third Down Conversions ", "3 Third Downs Failed "], "Chiefs, Kansas City KCC ST": ["1 Punts Inside 20 ", "4 Extra Points ", "40 yd Field Goal ", "21 Punt Return Yards ", "104 yd Kickoff Return TD ", "117 Kickoff Return Yards ", "0 Fumbles Lost on Special Teams ", "39 Penalty Yards "], "Chiefs, Kansas City KCC TM": [], "Chiefs, Kansas City KCC TMDB": [], "Chiefs, Kansas City KCC TMDL": [], "Chiefs, Kansas City KCC TMLB": ["11 Assists ", "4 Tackles for a Loss ", "1.0 Sacked a QB ", "14 Tackles "], "Chiefs, Kansas City KCC TMPK": [], "Chiefs, Kansas City KCC TMPN": [], "Chiefs, Kansas City KCC TMQB": ["21 Rushing Yards ", "1 Passing TDs ", "1 Interceptions ", "174 Passing Yards ", "7 Rushes ", "0 Fumbles Lost (to Opponent) "], "Chiefs, Kansas City KCC TMRB": ["5 Receptions ", "141 Rushing Yards ", "26 Receiving Yards ", "2 Rushing TDs ", "16 Rushes ", "0 Fumbles Lost (to Opponent) ", "1 Tackles "], "Chiefs, Kansas City KCC TMTE": ["0 Fumbles Lost (to Opponent) ", "25 Receiving Yards ", "4 Receptions "], "Chiefs, Kansas City KCC TMWR": ["7 Receptions ", "1 Receiving TDs ", "123 Receiving Yards ", "21 Punt Return Yards ", "117 Kickoff Return Yards ", "1 Kickoff Return TDs ", "0 Fumbles Lost (to Opponent) ", "7 Receptions "]}